LICENSE
NOTICE
setup.cfg
setup.py
coppertop/_structs/_tvarray.py
coppertop/_structs/_tvlist.py
coppertop/_structs/_tvmap.py
coppertop/_structs/_tvstruct.py
coppertop/_structs/tests/test_tvlist.py
coppertop/_structs/tests/test_tvstruct.py
coppertop/std/__init__.py
coppertop/std/accessing.py
coppertop/std/combining.py
coppertop/std/complex.py
coppertop/std/converting.py
coppertop/std/datetime.py
coppertop/std/dividing.py
coppertop/std/files.py
coppertop/std/generating.py
coppertop/std/linalg.py
coppertop/std/maths.py
coppertop/std/meta.py
coppertop/std/misc.py
coppertop/std/range.py
coppertop/std/reordering.py
coppertop/std/searching.py
coppertop/std/stats.py
coppertop/std/stdio.py
coppertop/std/structs.py
coppertop/std/testing.py
coppertop/std/text.py
coppertop/std/transforming.py
coppertop/std/types.py
coppertop/std/unicode.py
coppertop/std/vec.py
coppertop/std/_linalg/core.py
coppertop/std/_linalg/decomp.py
coppertop/std/_linalg/tests/test_linealg_core.py
coppertop/std/_stats/core.py
coppertop/std/examples/count_lines_jsp.py
coppertop/std/examples/format.py
coppertop/std/examples/format_calendar.py
coppertop/std/examples/linalg.py
coppertop/std/examples/misc.py
coppertop/std/examples/tests/test_count_lines_jsp.py
coppertop/std/examples/tests/test_format_calendar.py
coppertop/std/examples/tests/test_lazy_vs_eager.py
coppertop/std/examples/tests/test_misc.py
coppertop/std/tests/test_accessing.py
coppertop/std/tests/test_agg.py
coppertop/std/tests/test_agg_us_yields.py
coppertop/std/tests/test_range.py
coppertop/std/tests/test_std.py
coppertop_std.egg-info/PKG-INFO
coppertop_std.egg-info/SOURCES.txt
coppertop_std.egg-info/dependency_links.txt
coppertop_std.egg-info/not-zip-safe
coppertop_std.egg-info/requires.txt
coppertop_std.egg-info/top_level.txt