Metadata-Version: 2.1
Name: coppertop-std
Version: 2022.3.6
Summary: Some stats utils for bayesian analysis
Home-page: https://github.com/DangerMouseB/coppertop
Download-URL: 
Author: David Briant
Author-email: dangermouseb@forwarding.cc
License: BSD
Platform: UNKNOWN
Classifier: Development Status :: 4 - Beta
Classifier: Intended Audience :: Developers
Classifier: Intended Audience :: End Users/Desktop
Classifier: Intended Audience :: Science/Research
Classifier: Topic :: Utilities
Classifier: License :: OSI Approved :: BSD License
Classifier: Programming Language :: Python :: 3.8
Classifier: Programming Language :: Python :: 3.9
Requires-Python: >=3.8
License-File: LICENSE
License-File: NOTICE
